{
    "idSave": 27,
    "isFirstSession": false,
    "language": "ru",
    "promptDone": false,
    "money": 1,
    "newPlayerName": "Hello!",
    "openLevels": [
        false,
        true,
        false
    ],
    "level": 12,
    "gold": 16590,
    "WeaponDatas": [
        {
            "available": true,
            "amountOfAmmo": 105
        },
        {
            "available": true,
            "amountOfAmmo": 108
        },
        {
            "available": true,
            "amountOfAmmo": 0
        },
        {
            "available": true,
            "amountOfAmmo": 0
        },
        {
            "available": true,
            "amountOfAmmo": 0
        },
        {
            "available": true,
            "amountOfAmmo": 32
        },
        {
            "available": false,
            "amountOfAmmo": 12
        },
        {
            "available": true,
            "amountOfAmmo": 630
        },
        {
            "available": false,
            "amountOfAmmo": 5
        }
    ],
    "rotationCameraSpeed": 350.0
}